Ligare/programming/__init__.py
Ligare/programming/application.py
Ligare/programming/dependency_injection.py
Ligare/programming/exception.py
Ligare/programming/py.typed
Ligare/programming/R/__init__.py
Ligare/programming/R/exception.py
Ligare/programming/R/process.py
Ligare/programming/R/type_conversion.py
Ligare/programming/R/ui/types.py
Ligare/programming/cli/__init__.py
Ligare/programming/cli/argparse.py
Ligare/programming/collections/__init__.py
Ligare/programming/collections/dict.py
Ligare/programming/config/__init__.py
Ligare/programming/config/exceptions.py
Ligare/programming/patterns/__init__.py
Ligare/programming/patterns/dependency_injection.py
Ligare/programming/patterns/singleton.py
Ligare/programming/str/__init__.py
ligare_programming-0.7.1.dist-info/licenses/LICENSE.md
test/unit/test_argparse.py
test/unit/test_config.py
test/unit/test_dependency_injection.py
test/unit/R/test_process.py
test/unit/R/test_type_conversion.py
test/unit/patterns/test_dependency_injection.py
test/unit/patterns/test_singleton.py
ligare_programming-0.7.1.dist-info/METADATA
ligare_programming-0.7.1.dist-info/WHEEL
ligare_programming-0.7.1.dist-info/top_level.txt
ligare_programming-0.7.1.dist-info/RECORD
