Metadata-Version: 2.4
Name: Ligare.programming
Version: 0.7.1
Summary: Libraries for writing software.
Author-email: Aaron Holmes <aholmes@mednet.ucla.edu>
Project-URL: Homepage, https://github.com/uclahs-cds/Ligare
Project-URL: Bug Tracker, https://github.com/uclahs-cds/Ligare/issues
Project-URL: Repository, https://github.com/uclahs-cds/Ligare.git
Project-URL: Changelog, https://github.com/uclahs-cds/Ligare/blob/main/CHANGELOG.md
Classifier: Programming Language :: Python :: 3
Classifier: License :: OSI Approved :: GNU General Public License (GPL)
Classifier: Operating System :: OS Independent
Classifier: Topic :: Scientific/Engineering
Classifier: Topic :: Software Development :: Libraries
Classifier: Topic :: Software Development :: Libraries :: Application Frameworks
Classifier: Intended Audience :: Science/Research
Classifier: Intended Audience :: Developers
Classifier: Development Status :: 4 - Beta
Classifier: Natural Language :: English
Requires-Python: >=3.10
License-File: LICENSE.md
Requires-Dist: injector
Requires-Dist: pydantic
Requires-Dist: toml
Provides-Extra: aws
Requires-Dist: Ligare.AWS; extra == "aws"
Dynamic: license-file
